data_vault/__init__.py
data_vault/action.py
data_vault/actions.py
data_vault/dynamic_vault.py
data_vault/frames.py
data_vault/memory.py
data_vault/parameters.py
data_vault/parsing.py
data_vault/seven_zip.py
data_vault/vault.py
data_vault-0.4.4.dist-info/LICENSE
data_vault-0.4.4.dist-info/METADATA
data_vault-0.4.4.dist-info/WHEEL
data_vault-0.4.4.dist-info/top_level.txt
data_vault-0.4.4.dist-info/RECORD
