Metadata-Version: 2.1
Name: data-vault
Version: 0.4.4
Summary: IPython magic for simple, organized, compressed and encrypted: storage & transfer of files between notebooks
Home-page: https://github.com/krassowski/data-vault
Author: Michal Krassowski
Author-email: krassowski.michal+pypi@gmail.com
License: MIT
Keywords: jupyter,jupyterlab,notebook,ipython,storage,store,magic,vault
Platform: UNKNOWN
Classifier: Development Status :: 5 - Production/Stable
Classifier: License :: OSI Approved :: MIT License
Classifier: Framework :: IPython
Classifier: Framework :: Jupyter
Classifier: Operating System :: Microsoft :: Windows
Classifier: Operating System :: POSIX :: Linux
Classifier: Operating System :: MacOS
Classifier: Topic :: Utilities
Classifier: Topic :: Database
Classifier: Topic :: System :: Archiving
Classifier: Topic :: System :: Archiving :: Compression
Classifier: Topic :: Software Development :: User Interfaces
Classifier: Topic :: Software Development :: Libraries :: Python Modules
Classifier: Intended Audience :: Developers
Classifier: Intended Audience :: Science/Research
Classifier: Programming Language :: Python :: 3.6
Classifier: Programming Language :: Python :: 3.7
Requires-Dist: pandas
Requires-Dist: IPython
